{"segment_labels": [{"bird": {"category_entities_description": ["animal"], "positions": ["0.0:15.166666"], "confidence": [0.5357887744903564]}}, {"animal": {"category_entities_description": [], "positions": ["0.0:15.166666"], "confidence": [0.653359055519104]}}], "shot_labelshow": [{"tutorial": {"shot_label_category_entities": [], "positions": ["2.033333:3.466666", "5.033333:6.5"], "confidence": [0.7623473405838013, 0.8299393653869629]}}, {"how-to": {"shot_label_category_entities": [], "positions": ["2.033333:3.466666", "3.5:5.0", "5.033333:6.5", "10.566666:11.966666"], "confidence": [0.5385726094245911, 0.385641485452652, 0.5362932682037354, 0.385641485452652]}}, {"petal": {"shot_label_category_entities": [], "positions": ["2.033333:3.466666"], "confidence": [0.3603615462779999]}}, {"flower": {"shot_label_category_entities": ["plant"], "positions": ["2.033333:3.466666"], "confidence": [0.31733933091163635]}}, {"text": {"shot_label_category_entities": [], "positions": ["7.533333:9.066666", "9.1:10.533333"], "confidence": [0.42520982027053833, 0.42520982027053833]}}, {"food": {"shot_label_category_entities": [], "positions": ["12.0:15.166666"], "confidence": [0.8072111010551453]}}, {"hand": {"shot_label_category_entities": [], "positions": ["5.033333:6.5", "6.533333:7.5", "9.1:10.533333"], "confidence": [0.6140938401222229, 0.5101560354232788, 0.424079567193985]}}, {"animal": {"shot_label_category_entities": [], "positions": ["3.5:5.0", "5.033333:6.5"], "confidence": [0.6990489959716797, 0.6055097579956055]}}, {"finger": {"shot_label_category_entities": ["hand"], "positions": ["5.033333:6.5", "6.533333:7.5", "9.1:10.533333"], "confidence": [0.5804758667945862, 0.49381962418556213, 0.41916167736053467]}}, {"craft": {"shot_label_category_entities": ["art"], "positions": ["2.033333:3.466666", "3.5:5.0"], "confidence": [0.7308588624000549, 0.43513303995132446]}}, {"bird": {"shot_label_category_entities": ["animal"], "positions": ["3.5:5.0", "5.033333:6.5"], "confidence": [0.5957297086715698, 0.43990790843963623]}}], "frame_labels": []}