{"segment_labels": [{"song": {"category_entities_description": ["music"], "positions": ["0.0:7.366666"], "confidence": [0.8198216557502747]}}, {"animation": {"category_entities_description": [], "positions": ["0.0:7.366666"], "confidence": [0.7744234204292297]}}, {"poster": {"category_entities_description": [], "positions": ["0.0:7.366666"], "confidence": [0.32745859026908875]}}], "shot_labelshow": [{"song": {"shot_label_category_entities": ["music"], "positions": ["0.0:3.25", "3.266666:6.133333"], "confidence": [0.8324964046478271, 0.5851970911026001]}}, {"poster": {"shot_label_category_entities": [], "positions": ["0.0:3.25", "6.15:7.366666"], "confidence": [0.3568984270095825, 0.4924052357673645]}}, {"animation": {"shot_label_category_entities": [], "positions": ["0.0:3.25"], "confidence": [0.3364885449409485]}}, {"anime": {"shot_label_category_entities": ["artwork"], "positions": ["0.0:3.25"], "confidence": [0.3178528845310211]}}, {"visual effects": {"shot_label_category_entities": ["person"], "positions": ["3.266666:6.133333", "6.15:7.366666"], "confidence": [0.6851027011871338, 0.7566317319869995]}}, {"illustration": {"shot_label_category_entities": ["art"], "positions": ["0.0:3.25"], "confidence": [0.6349786520004272]}}, {"3d modeling": {"shot_label_category_entities": ["person"], "positions": ["3.266666:6.133333"], "confidence": [0.38873109221458435]}}, {"graphic design": {"shot_label_category_entities": ["artwork"], "positions": ["0.0:3.25"], "confidence": [0.4734857976436615]}}], "frame_labels": []}